pyrill/__init__.py
pyrill/__version__.py
pyrill/accumulators.py
pyrill/base.py
pyrill/bus.py
pyrill/bytes.py
pyrill/chunks.py
pyrill/csv.py
pyrill/debug.py
pyrill/io.py
pyrill/json.py
pyrill/lists.py
pyrill/mappers.py
pyrill/primitives.py
pyrill/queues.py
pyrill/sinks.py
pyrill/sources.py
pyrill/strings.py
pyrill/strlike.py
pyrill/utils.py
pyrill-0.1.10.dist-info/LICENSE
pyrill-0.1.10.dist-info/METADATA
pyrill-0.1.10.dist-info/WHEEL
pyrill-0.1.10.dist-info/top_level.txt
pyrill-0.1.10.dist-info/zip-safe
pyrill-0.1.10.dist-info/RECORD
