Metadata-Version: 2.1
Name: pyrill
Version: 0.1.10
Summary: Asynchronous streams for Python
Home-page: https://github.com/pyrill-framework/pyrill
Author: Alfred Santacatalina
Author-email: alfred82santa@gmail.com
License: UNKNOWN
Platform: UNKNOWN
Classifier: Intended Audience :: Developers
Classifier: Programming Language :: Python
Classifier: Programming Language :: Python :: 3.6
Classifier: Programming Language :: Python :: 3.7
Classifier: Programming Language :: Python :: 3.8
Classifier: Programming Language :: Python :: 3.9
Classifier: Programming Language :: Python :: 3.10
Classifier: Development Status :: 4 - Beta
License-File: LICENSE
Requires-Dist: dataclasses ; python_version<'3.7'
Requires-Dist: async-exit-stack ; python_version<'3.7'
Requires-Dist: typing-extensions ; python_version<'3.8'
